xenqore/__init__.py
xenqore/apps.py
xenqore/constants.py
xenqore/datatypes.py
xenqore/device.py
xenqore/layers.py
xenqore/math.py
xenqore/utils.py
xenqore_project-1.0.dist-info/METADATA
xenqore_project-1.0.dist-info/WHEEL
xenqore_project-1.0.dist-info/top_level.txt
xenqore_project-1.0.dist-info/RECORD
